{
  "version": "7",
  "dialect": "postgresql",
  "tables": {
    "public.users_roles": {
      "name": "users_roles",
      "schema": "",
      "columns": {
        "order": {
          "name": "order",
          "type": "integer",
          "primaryKey": false,
          "notNull": true
        },
        "parent_id": {
          "name": "parent_id",
          "type": "integer",
          "primaryKey": false,
          "notNull": true
        },
        "value": {
          "name": "value",
          "type": "enum_users_roles",
          "typeSchema": "public",
          "primaryKey": false,
          "notNull": false
        },
        "id": {
          "name": "id",
          "type": "serial",
          "primaryKey": true,
          "notNull": true
        }
      },
      "indexes": {
        "users_roles_order_idx": {
          "name": "users_roles_order_idx",
          "columns": [
            {
              "expression": "order",
              "isExpression": false,
              "asc": true,
              "nulls": "last"
            }
          ],
          "isUnique": false,
          "concurrently": false,
          "method": "btree",
          "with": {}
        },
        "users_roles_parent_idx": {
          "name": "users_roles_parent_idx",
          "columns": [
            {
              "expression": "parent_id",
              "isExpression": false,
              "asc": true,
              "nulls": "last"
            }
          ],
          "isUnique": false,
          "concurrently": false,
          "method": "btree",
          "with": {}
        }
      },
      "foreignKeys": {
        "users_roles_parent_fk": {
          "name": "users_roles_parent_fk",
          "tableFrom": "users_roles",
          "tableTo": "users",
          "columnsFrom": [
            "parent_id"
          ],
          "columnsTo": [
            "id"
          ],
          "onDelete": "cascade",
          "onUpdate": "no action"
        }
      },
      "compositePrimaryKeys": {},
      "uniqueConstraints": {},
      "policies": {},
      "checkConstraints": {},
      "isRLSEnabled": false
    },
    "public.users_sessions": {
      "name": "users_sessions",
      "schema": "",
      "columns": {
        "_order": {
          "name": "_order",
          "type": "integer",
          "primaryKey": false,
          "notNull": true
        },
        "_parent_id": {
          "name": "_parent_id",
          "type": "integer",
          "primaryKey": false,
          "notNull": true
        },
        "id": {
          "name": "id",
          "type": "varchar",
          "primaryKey": true,
          "notNull": true
        },
        "created_at": {
          "name": "created_at",
          "type": "timestamp(3) with time zone",
          "primaryKey": false,
          "notNull": false
        },
        "expires_at": {
          "name": "expires_at",
          "type": "timestamp(3) with time zone",
          "primaryKey": false,
          "notNull": true
        }
      },
      "indexes": {
        "users_sessions_order_idx": {
          "name": "users_sessions_order_idx",
          "columns": [
            {
              "expression": "_order",
              "isExpression": false,
              "asc": true,
              "nulls": "last"
            }
          ],
          "isUnique": false,
          "concurrently": false,
          "method": "btree",
          "with": {}
        },
        "users_sessions_parent_id_idx": {
          "name": "users_sessions_parent_id_idx",
          "columns": [
            {
              "expression": "_parent_id",
              "isExpression": false,
              "asc": true,
              "nulls": "last"
            }
          ],
          "isUnique": false,
          "concurrently": false,
          "method": "btree",
          "with": {}
        }
      },
      "foreignKeys": {
        "users_sessions_parent_id_fk": {
          "name": "users_sessions_parent_id_fk",
          "tableFrom": "users_sessions",
          "tableTo": "users",
          "columnsFrom": [
            "_parent_id"
          ],
          "columnsTo": [
            "id"
          ],
          "onDelete": "cascade",
          "onUpdate": "no action"
        }
      },
      "compositePrimaryKeys": {},
      "uniqueConstraints": {},
      "policies": {},
      "checkConstraints": {},
      "isRLSEnabled": false
    },
    "public.users": {
      "name": "users",
      "schema": "",
      "columns": {
        "id": {
          "name": "id",
          "type": "serial",
          "primaryKey": true,
          "notNull": true
        },
        "updated_at": {
          "name": "updated_at",
          "type": "timestamp(3) with time zone",
          "primaryKey": false,
          "notNull": true,
          "default": "now()"
        },
        "created_at": {
          "name": "created_at",
          "type": "timestamp(3) with time zone",
          "primaryKey": false,
          "notNull": true,
          "default": "now()"
        },
        "email": {
          "name": "email",
          "type": "varchar",
          "primaryKey": false,
          "notNull": true
        },
        "reset_password_token": {
          "name": "reset_password_token",
          "type": "varchar",
          "primaryKey": false,
          "notNull": false
        },
        "reset_password_expiration": {
          "name": "reset_password_expiration",
          "type": "timestamp(3) with time zone",
          "primaryKey": false,
          "notNull": false
        },
        "salt": {
          "name": "salt",
          "type": "varchar",
          "primaryKey": false,
          "notNull": false
        },
        "hash": {
          "name": "hash",
          "type": "varchar",
          "primaryKey": false,
          "notNull": false
        },
        "login_attempts": {
          "name": "login_attempts",
          "type": "numeric",
          "primaryKey": false,
          "notNull": false,
          "default": 0
        },
        "lock_until": {
          "name": "lock_until",
          "type": "timestamp(3) with time zone",
          "primaryKey": false,
          "notNull": false
        }
      },
      "indexes": {
        "users_updated_at_idx": {
          "name": "users_updated_at_idx",
          "columns": [
            {
              "expression": "updated_at",
              "isExpression": false,
              "asc": true,
              "nulls": "last"
            }
          ],
          "isUnique": false,
          "concurrently": false,
          "method": "btree",
          "with": {}
        },
        "users_created_at_idx": {
          "name": "users_created_at_idx",
          "columns": [
            {
              "expression": "created_at",
              "isExpression": false,
              "asc": true,
              "nulls": "last"
            }
          ],
          "isUnique": false,
          "concurrently": false,
          "method": "btree",
          "with": {}
        },
        "users_email_idx": {
          "name": "users_email_idx",
          "columns": [
            {
              "expression": "email",
              "isExpression": false,
              "asc": true,
              "nulls": "last"
            }
          ],
          "isUnique": true,
          "concurrently": false,
          "method": "btree",
          "with": {}
        }
      },
      "foreignKeys": {},
      "compositePrimaryKeys": {},
      "uniqueConstraints": {},
      "policies": {},
      "checkConstraints": {},
      "isRLSEnabled": false
    },
    "public.media": {
      "name": "media",
      "schema": "",
      "columns": {
        "id": {
          "name": "id",
          "type": "serial",
          "primaryKey": true,
          "notNull": true
        },
        "alt": {
          "name": "alt",
          "type": "varchar",
          "primaryKey": false,
          "notNull": true
        },
        "updated_at": {
          "name": "updated_at",
          "type": "timestamp(3) with time zone",
          "primaryKey": false,
          "notNull": true,
          "default": "now()"
        },
        "created_at": {
          "name": "created_at",
          "type": "timestamp(3) with time zone",
          "primaryKey": false,
          "notNull": true,
          "default": "now()"
        },
        "url": {
          "name": "url",
          "type": "varchar",
          "primaryKey": false,
          "notNull": false
        },
        "thumbnail_u_r_l": {
          "name": "thumbnail_u_r_l",
          "type": "varchar",
          "primaryKey": false,
          "notNull": false
        },
        "filename": {
          "name": "filename",
          "type": "varchar",
          "primaryKey": false,
          "notNull": false
        },
        "mime_type": {
          "name": "mime_type",
          "type": "varchar",
          "primaryKey": false,
          "notNull": false
        },
        "filesize": {
          "name": "filesize",
          "type": "numeric",
          "primaryKey": false,
          "notNull": false
        },
        "width": {
          "name": "width",
          "type": "numeric",
          "primaryKey": false,
          "notNull": false
        },
        "height": {
          "name": "height",
          "type": "numeric",
          "primaryKey": false,
          "notNull": false
        },
        "focal_x": {
          "name": "focal_x",
          "type": "numeric",
          "primaryKey": false,
          "notNull": false
        },
        "focal_y": {
          "name": "focal_y",
          "type": "numeric",
          "primaryKey": false,
          "notNull": false
        }
      },
      "indexes": {
        "media_updated_at_idx": {
          "name": "media_updated_at_idx",
          "columns": [
            {
              "expression": "updated_at",
              "isExpression": false,
              "asc": true,
              "nulls": "last"
            }
          ],
          "isUnique": false,
          "concurrently": false,
          "method": "btree",
          "with": {}
        },
        "media_created_at_idx": {
          "name": "media_created_at_idx",
          "columns": [
            {
              "expression": "created_at",
              "isExpression": false,
              "asc": true,
              "nulls": "last"
            }
          ],
          "isUnique": false,
          "concurrently": false,
          "method": "btree",
          "with": {}
        },
        "media_filename_idx": {
          "name": "media_filename_idx",
          "columns": [
            {
              "expression": "filename",
              "isExpression": false,
              "asc": true,
              "nulls": "last"
            }
          ],
          "isUnique": true,
          "concurrently": false,
          "method": "btree",
          "with": {}
        }
      },
      "foreignKeys": {},
      "compositePrimaryKeys": {},
      "uniqueConstraints": {},
      "policies": {},
      "checkConstraints": {},
      "isRLSEnabled": false
    },
    "public.services": {
      "name": "services",
      "schema": "",
      "columns": {
        "id": {
          "name": "id",
          "type": "serial",
          "primaryKey": true,
          "notNull": true
        },
        "name": {
          "name": "name",
          "type": "varchar",
          "primaryKey": false,
          "notNull": true
        },
        "slug": {
          "name": "slug",
          "type": "varchar",
          "primaryKey": false,
          "notNull": true
        },
        "description": {
          "name": "description",
          "type": "varchar",
          "primaryKey": false,
          "notNull": true
        },
        "icon_source": {
          "name": "icon_source",
          "type": "enum_services_icon_source",
          "typeSchema": "public",
          "primaryKey": false,
          "notNull": false,
          "default": "'lucide'"
        },
        "icon_lucide": {
          "name": "icon_lucide",
          "type": "enum_services_icon_lucide",
          "typeSchema": "public",
          "primaryKey": false,
          "notNull": false,
          "default": "'BookOpen'"
        },
        "icon_custom_svg_id": {
          "name": "icon_custom_svg_id",
          "type": "integer",
          "primaryKey": false,
          "notNull": false
        },
        "theme_primary_color": {
          "name": "theme_primary_color",
          "type": "varchar",
          "primaryKey": false,
          "notNull": false
        },
        "theme_secondary_color": {
          "name": "theme_secondary_color",
          "type": "varchar",
          "primaryKey": false,
          "notNull": false
        },
        "theme_accent_color": {
          "name": "theme_accent_color",
          "type": "varchar",
          "primaryKey": false,
          "notNull": false
        },
        "theme_logo_id": {
          "name": "theme_logo_id",
          "type": "integer",
          "primaryKey": false,
          "notNull": false
        },
        "search_defaults_placeholder": {
          "name": "search_defaults_placeholder",
          "type": "varchar",
          "primaryKey": false,
          "notNull": false
        },
        "search_defaults_include_older_versions": {
          "name": "search_defaults_include_older_versions",
          "type": "boolean",
          "primaryKey": false,
          "notNull": false,
          "default": false
        },
        "search_defaults_results_limit": {
          "name": "search_defaults_results_limit",
          "type": "numeric",
          "primaryKey": false,
          "notNull": false,
          "default": 20
        },
        "latest_version_id": {
          "name": "latest_version_id",
          "type": "integer",
          "primaryKey": false,
          "notNull": false
        },
        "updated_at": {
          "name": "updated_at",
          "type": "timestamp(3) with time zone",
          "primaryKey": false,
          "notNull": true,
          "default": "now()"
        },
        "created_at": {
          "name": "created_at",
          "type": "timestamp(3) with time zone",
          "primaryKey": false,
          "notNull": true,
          "default": "now()"
        }
      },
      "indexes": {
        "services_slug_idx": {
          "name": "services_slug_idx",
          "columns": [
            {
              "expression": "slug",
              "isExpression": false,
              "asc": true,
              "nulls": "last"
            }
          ],
          "isUnique": true,
          "concurrently": false,
          "method": "btree",
          "with": {}
        },
        "services_icon_icon_custom_svg_idx": {
          "name": "services_icon_icon_custom_svg_idx",
          "columns": [
            {
              "expression": "icon_custom_svg_id",
              "isExpression": false,
              "asc": true,
              "nulls": "last"
            }
          ],
          "isUnique": false,
          "concurrently": false,
          "method": "btree",
          "with": {}
        },
        "services_theme_theme_logo_idx": {
          "name": "services_theme_theme_logo_idx",
          "columns": [
            {
              "expression": "theme_logo_id",
              "isExpression": false,
              "asc": true,
              "nulls": "last"
            }
          ],
          "isUnique": false,
          "concurrently": false,
          "method": "btree",
          "with": {}
        },
        "services_latest_version_idx": {
          "name": "services_latest_version_idx",
          "columns": [
            {
              "expression": "latest_version_id",
              "isExpression": false,
              "asc": true,
              "nulls": "last"
            }
          ],
          "isUnique": false,
          "concurrently": false,
          "method": "btree",
          "with": {}
        },
        "services_updated_at_idx": {
          "name": "services_updated_at_idx",
          "columns": [
            {
              "expression": "updated_at",
              "isExpression": false,
              "asc": true,
              "nulls": "last"
            }
          ],
          "isUnique": false,
          "concurrently": false,
          "method": "btree",
          "with": {}
        },
        "services_created_at_idx": {
          "name": "services_created_at_idx",
          "columns": [
            {
              "expression": "created_at",
              "isExpression": false,
              "asc": true,
              "nulls": "last"
            }
          ],
          "isUnique": false,
          "concurrently": false,
          "method": "btree",
          "with": {}
        }
      },
      "foreignKeys": {
        "services_icon_custom_svg_id_media_id_fk": {
          "name": "services_icon_custom_svg_id_media_id_fk",
          "tableFrom": "services",
          "tableTo": "media",
          "columnsFrom": [
            "icon_custom_svg_id"
          ],
          "columnsTo": [
            "id"
          ],
          "onDelete": "set null",
          "onUpdate": "no action"
        },
        "services_theme_logo_id_media_id_fk": {
          "name": "services_theme_logo_id_media_id_fk",
          "tableFrom": "services",
          "tableTo": "media",
          "columnsFrom": [
            "theme_logo_id"
          ],
          "columnsTo": [
            "id"
          ],
          "onDelete": "set null",
          "onUpdate": "no action"
        },
        "services_latest_version_id_doc_versions_id_fk": {
          "name": "services_latest_version_id_doc_versions_id_fk",
          "tableFrom": "services",
          "tableTo": "doc_versions",
          "columnsFrom": [
            "latest_version_id"
          ],
          "columnsTo": [
            "id"
          ],
          "onDelete": "set null",
          "onUpdate": "no action"
        }
      },
      "compositePrimaryKeys": {},
      "uniqueConstraints": {},
      "policies": {},
      "checkConstraints": {},
      "isRLSEnabled": false
    },
    "public.doc_versions": {
      "name": "doc_versions",
      "schema": "",
      "columns": {
        "id": {
          "name": "id",
          "type": "serial",
          "primaryKey": true,
          "notNull": true
        },
        "service_id": {
          "name": "service_id",
          "type": "integer",
          "primaryKey": false,
          "notNull": true
        },
        "version": {
          "name": "version",
          "type": "varchar",
          "primaryKey": false,
          "notNull": true
        },
        "default_page_slug": {
          "name": "default_page_slug",
          "type": "varchar",
          "primaryKey": false,
          "notNull": true
        },
        "version_key": {
          "name": "version_key",
          "type": "varchar",
          "primaryKey": false,
          "notNull": false
        },
        "is_prerelease": {
          "name": "is_prerelease",
          "type": "boolean",
          "primaryKey": false,
          "notNull": false,
          "default": false
        },
        "status": {
          "name": "status",
          "type": "enum_doc_versions_status",
          "typeSchema": "public",
          "primaryKey": false,
          "notNull": true,
          "default": "'draft'"
        },
        "updated_at": {
          "name": "updated_at",
          "type": "timestamp(3) with time zone",
          "primaryKey": false,
          "notNull": true,
          "default": "now()"
        },
        "created_at": {
          "name": "created_at",
          "type": "timestamp(3) with time zone",
          "primaryKey": false,
          "notNull": true,
          "default": "now()"
        }
      },
      "indexes": {
        "doc_versions_service_idx": {
          "name": "doc_versions_service_idx",
          "columns": [
            {
              "expression": "service_id",
              "isExpression": false,
              "asc": true,
              "nulls": "last"
            }
          ],
          "isUnique": false,
          "concurrently": false,
          "method": "btree",
          "with": {}
        },
        "doc_versions_updated_at_idx": {
          "name": "doc_versions_updated_at_idx",
          "columns": [
            {
              "expression": "updated_at",
              "isExpression": false,
              "asc": true,
              "nulls": "last"
            }
          ],
          "isUnique": false,
          "concurrently": false,
          "method": "btree",
          "with": {}
        },
        "doc_versions_created_at_idx": {
          "name": "doc_versions_created_at_idx",
          "columns": [
            {
              "expression": "created_at",
              "isExpression": false,
              "asc": true,
              "nulls": "last"
            }
          ],
          "isUnique": false,
          "concurrently": false,
          "method": "btree",
          "with": {}
        }
      },
      "foreignKeys": {
        "doc_versions_service_id_services_id_fk": {
          "name": "doc_versions_service_id_services_id_fk",
          "tableFrom": "doc_versions",
          "tableTo": "services",
          "columnsFrom": [
            "service_id"
          ],
          "columnsTo": [
            "id"
          ],
          "onDelete": "set null",
          "onUpdate": "no action"
        }
      },
      "compositePrimaryKeys": {},
      "uniqueConstraints": {},
      "policies": {},
      "checkConstraints": {},
      "isRLSEnabled": false
    },
    "public.doc_page_groups": {
      "name": "doc_page_groups",
      "schema": "",
      "columns": {
        "id": {
          "name": "id",
          "type": "serial",
          "primaryKey": true,
          "notNull": true
        },
        "service_id": {
          "name": "service_id",
          "type": "integer",
          "primaryKey": false,
          "notNull": true
        },
        "version_id": {
          "name": "version_id",
          "type": "integer",
          "primaryKey": false,
          "notNull": true
        },
        "name": {
          "name": "name",
          "type": "varchar",
          "primaryKey": false,
          "notNull": true
        },
        "slug": {
          "name": "slug",
          "type": "varchar",
          "primaryKey": false,
          "notNull": false
        },
        "description": {
          "name": "description",
          "type": "varchar",
          "primaryKey": false,
          "notNull": false
        },
        "order": {
          "name": "order",
          "type": "numeric",
          "primaryKey": false,
          "notNull": false,
          "default": 0
        },
        "updated_at": {
          "name": "updated_at",
          "type": "timestamp(3) with time zone",
          "primaryKey": false,
          "notNull": true,
          "default": "now()"
        },
        "created_at": {
          "name": "created_at",
          "type": "timestamp(3) with time zone",
          "primaryKey": false,
          "notNull": true,
          "default": "now()"
        }
      },
      "indexes": {
        "doc_page_groups_service_idx": {
          "name": "doc_page_groups_service_idx",
          "columns": [
            {
              "expression": "service_id",
              "isExpression": false,
              "asc": true,
              "nulls": "last"
            }
          ],
          "isUnique": false,
          "concurrently": false,
          "method": "btree",
          "with": {}
        },
        "doc_page_groups_version_idx": {
          "name": "doc_page_groups_version_idx",
          "columns": [
            {
              "expression": "version_id",
              "isExpression": false,
              "asc": true,
              "nulls": "last"
            }
          ],
          "isUnique": false,
          "concurrently": false,
          "method": "btree",
          "with": {}
        },
        "doc_page_groups_slug_idx": {
          "name": "doc_page_groups_slug_idx",
          "columns": [
            {
              "expression": "slug",
              "isExpression": false,
              "asc": true,
              "nulls": "last"
            }
          ],
          "isUnique": false,
          "concurrently": false,
          "method": "btree",
          "with": {}
        },
        "doc_page_groups_updated_at_idx": {
          "name": "doc_page_groups_updated_at_idx",
          "columns": [
            {
              "expression": "updated_at",
              "isExpression": false,
              "asc": true,
              "nulls": "last"
            }
          ],
          "isUnique": false,
          "concurrently": false,
          "method": "btree",
          "with": {}
        },
        "doc_page_groups_created_at_idx": {
          "name": "doc_page_groups_created_at_idx",
          "columns": [
            {
              "expression": "created_at",
              "isExpression": false,
              "asc": true,
              "nulls": "last"
            }
          ],
          "isUnique": false,
          "concurrently": false,
          "method": "btree",
          "with": {}
        },
        "service_version_slug_idx": {
          "name": "service_version_slug_idx",
          "columns": [
            {
              "expression": "service_id",
              "isExpression": false,
              "asc": true,
              "nulls": "last"
            },
            {
              "expression": "version_id",
              "isExpression": false,
              "asc": true,
              "nulls": "last"
            },
            {
              "expression": "slug",
              "isExpression": false,
              "asc": true,
              "nulls": "last"
            }
          ],
          "isUnique": true,
          "concurrently": false,
          "method": "btree",
          "with": {}
        }
      },
      "foreignKeys": {
        "doc_page_groups_service_id_services_id_fk": {
          "name": "doc_page_groups_service_id_services_id_fk",
          "tableFrom": "doc_page_groups",
          "tableTo": "services",
          "columnsFrom": [
            "service_id"
          ],
          "columnsTo": [
            "id"
          ],
          "onDelete": "set null",
          "onUpdate": "no action"
        },
        "doc_page_groups_version_id_doc_versions_id_fk": {
          "name": "doc_page_groups_version_id_doc_versions_id_fk",
          "tableFrom": "doc_page_groups",
          "tableTo": "doc_versions",
          "columnsFrom": [
            "version_id"
          ],
          "columnsTo": [
            "id"
          ],
          "onDelete": "set null",
          "onUpdate": "no action"
        }
      },
      "compositePrimaryKeys": {},
      "uniqueConstraints": {},
      "policies": {},
      "checkConstraints": {},
      "isRLSEnabled": false
    },
    "public.doc_pages": {
      "name": "doc_pages",
      "schema": "",
      "columns": {
        "id": {
          "name": "id",
          "type": "serial",
          "primaryKey": true,
          "notNull": true
        },
        "service_id": {
          "name": "service_id",
          "type": "integer",
          "primaryKey": false,
          "notNull": true
        },
        "version_id": {
          "name": "version_id",
          "type": "integer",
          "primaryKey": false,
          "notNull": true
        },
        "slug": {
          "name": "slug",
          "type": "varchar",
          "primaryKey": false,
          "notNull": true
        },
        "group_id": {
          "name": "group_id",
          "type": "integer",
          "primaryKey": false,
          "notNull": false
        },
        "title": {
          "name": "title",
          "type": "varchar",
          "primaryKey": false,
          "notNull": true
        },
        "content": {
          "name": "content",
          "type": "jsonb",
          "primaryKey": false,
          "notNull": true
        },
        "status": {
          "name": "status",
          "type": "enum_doc_pages_status",
          "typeSchema": "public",
          "primaryKey": false,
          "notNull": true,
          "default": "'draft'"
        },
        "updated_at": {
          "name": "updated_at",
          "type": "timestamp(3) with time zone",
          "primaryKey": false,
          "notNull": true,
          "default": "now()"
        },
        "created_at": {
          "name": "created_at",
          "type": "timestamp(3) with time zone",
          "primaryKey": false,
          "notNull": true,
          "default": "now()"
        }
      },
      "indexes": {
        "doc_pages_service_idx": {
          "name": "doc_pages_service_idx",
          "columns": [
            {
              "expression": "service_id",
              "isExpression": false,
              "asc": true,
              "nulls": "last"
            }
          ],
          "isUnique": false,
          "concurrently": false,
          "method": "btree",
          "with": {}
        },
        "doc_pages_version_idx": {
          "name": "doc_pages_version_idx",
          "columns": [
            {
              "expression": "version_id",
              "isExpression": false,
              "asc": true,
              "nulls": "last"
            }
          ],
          "isUnique": false,
          "concurrently": false,
          "method": "btree",
          "with": {}
        },
        "doc_pages_group_idx": {
          "name": "doc_pages_group_idx",
          "columns": [
            {
              "expression": "group_id",
              "isExpression": false,
              "asc": true,
              "nulls": "last"
            }
          ],
          "isUnique": false,
          "concurrently": false,
          "method": "btree",
          "with": {}
        },
        "doc_pages_updated_at_idx": {
          "name": "doc_pages_updated_at_idx",
          "columns": [
            {
              "expression": "updated_at",
              "isExpression": false,
              "asc": true,
              "nulls": "last"
            }
          ],
          "isUnique": false,
          "concurrently": false,
          "method": "btree",
          "with": {}
        },
        "doc_pages_created_at_idx": {
          "name": "doc_pages_created_at_idx",
          "columns": [
            {
              "expression": "created_at",
              "isExpression": false,
              "asc": true,
              "nulls": "last"
            }
          ],
          "isUnique": false,
          "concurrently": false,
          "method": "btree",
          "with": {}
        },
        "service_version_slug_1_idx": {
          "name": "service_version_slug_1_idx",
          "columns": [
            {
              "expression": "service_id",
              "isExpression": false,
              "asc": true,
              "nulls": "last"
            },
            {
              "expression": "version_id",
              "isExpression": false,
              "asc": true,
              "nulls": "last"
            },
            {
              "expression": "slug",
              "isExpression": false,
              "asc": true,
              "nulls": "last"
            }
          ],
          "isUnique": true,
          "concurrently": false,
          "method": "btree",
          "with": {}
        }
      },
      "foreignKeys": {
        "doc_pages_service_id_services_id_fk": {
          "name": "doc_pages_service_id_services_id_fk",
          "tableFrom": "doc_pages",
          "tableTo": "services",
          "columnsFrom": [
            "service_id"
          ],
          "columnsTo": [
            "id"
          ],
          "onDelete": "set null",
          "onUpdate": "no action"
        },
        "doc_pages_version_id_doc_versions_id_fk": {
          "name": "doc_pages_version_id_doc_versions_id_fk",
          "tableFrom": "doc_pages",
          "tableTo": "doc_versions",
          "columnsFrom": [
            "version_id"
          ],
          "columnsTo": [
            "id"
          ],
          "onDelete": "set null",
          "onUpdate": "no action"
        },
        "doc_pages_group_id_doc_page_groups_id_fk": {
          "name": "doc_pages_group_id_doc_page_groups_id_fk",
          "tableFrom": "doc_pages",
          "tableTo": "doc_page_groups",
          "columnsFrom": [
            "group_id"
          ],
          "columnsTo": [
            "id"
          ],
          "onDelete": "set null",
          "onUpdate": "no action"
        }
      },
      "compositePrimaryKeys": {},
      "uniqueConstraints": {},
      "policies": {},
      "checkConstraints": {},
      "isRLSEnabled": false
    },
    "public.redirects": {
      "name": "redirects",
      "schema": "",
      "columns": {
        "id": {
          "name": "id",
          "type": "serial",
          "primaryKey": true,
          "notNull": true
        },
        "from": {
          "name": "from",
          "type": "varchar",
          "primaryKey": false,
          "notNull": true
        },
        "to": {
          "name": "to",
          "type": "varchar",
          "primaryKey": false,
          "notNull": true
        },
        "service_id": {
          "name": "service_id",
          "type": "integer",
          "primaryKey": false,
          "notNull": false
        },
        "version_id": {
          "name": "version_id",
          "type": "integer",
          "primaryKey": false,
          "notNull": false
        },
        "permanent": {
          "name": "permanent",
          "type": "boolean",
          "primaryKey": false,
          "notNull": false,
          "default": true
        },
        "updated_at": {
          "name": "updated_at",
          "type": "timestamp(3) with time zone",
          "primaryKey": false,
          "notNull": true,
          "default": "now()"
        },
        "created_at": {
          "name": "created_at",
          "type": "timestamp(3) with time zone",
          "primaryKey": false,
          "notNull": true,
          "default": "now()"
        }
      },
      "indexes": {
        "redirects_from_idx": {
          "name": "redirects_from_idx",
          "columns": [
            {
              "expression": "from",
              "isExpression": false,
              "asc": true,
              "nulls": "last"
            }
          ],
          "isUnique": false,
          "concurrently": false,
          "method": "btree",
          "with": {}
        },
        "redirects_service_idx": {
          "name": "redirects_service_idx",
          "columns": [
            {
              "expression": "service_id",
              "isExpression": false,
              "asc": true,
              "nulls": "last"
            }
          ],
          "isUnique": false,
          "concurrently": false,
          "method": "btree",
          "with": {}
        },
        "redirects_version_idx": {
          "name": "redirects_version_idx",
          "columns": [
            {
              "expression": "version_id",
              "isExpression": false,
              "asc": true,
              "nulls": "last"
            }
          ],
          "isUnique": false,
          "concurrently": false,
          "method": "btree",
          "with": {}
        },
        "redirects_updated_at_idx": {
          "name": "redirects_updated_at_idx",
          "columns": [
            {
              "expression": "updated_at",
              "isExpression": false,
              "asc": true,
              "nulls": "last"
            }
          ],
          "isUnique": false,
          "concurrently": false,
          "method": "btree",
          "with": {}
        },
        "redirects_created_at_idx": {
          "name": "redirects_created_at_idx",
          "columns": [
            {
              "expression": "created_at",
              "isExpression": false,
              "asc": true,
              "nulls": "last"
            }
          ],
          "isUnique": false,
          "concurrently": false,
          "method": "btree",
          "with": {}
        }
      },
      "foreignKeys": {
        "redirects_service_id_services_id_fk": {
          "name": "redirects_service_id_services_id_fk",
          "tableFrom": "redirects",
          "tableTo": "services",
          "columnsFrom": [
            "service_id"
          ],
          "columnsTo": [
            "id"
          ],
          "onDelete": "set null",
          "onUpdate": "no action"
        },
        "redirects_version_id_doc_versions_id_fk": {
          "name": "redirects_version_id_doc_versions_id_fk",
          "tableFrom": "redirects",
          "tableTo": "doc_versions",
          "columnsFrom": [
            "version_id"
          ],
          "columnsTo": [
            "id"
          ],
          "onDelete": "set null",
          "onUpdate": "no action"
        }
      },
      "compositePrimaryKeys": {},
      "uniqueConstraints": {},
      "policies": {},
      "checkConstraints": {},
      "isRLSEnabled": false
    },
    "public.payload_kv": {
      "name": "payload_kv",
      "schema": "",
      "columns": {
        "id": {
          "name": "id",
          "type": "serial",
          "primaryKey": true,
          "notNull": true
        },
        "key": {
          "name": "key",
          "type": "varchar",
          "primaryKey": false,
          "notNull": true
        },
        "data": {
          "name": "data",
          "type": "jsonb",
          "primaryKey": false,
          "notNull": true
        }
      },
      "indexes": {
        "payload_kv_key_idx": {
          "name": "payload_kv_key_idx",
          "columns": [
            {
              "expression": "key",
              "isExpression": false,
              "asc": true,
              "nulls": "last"
            }
          ],
          "isUnique": true,
          "concurrently": false,
          "method": "btree",
          "with": {}
        }
      },
      "foreignKeys": {},
      "compositePrimaryKeys": {},
      "uniqueConstraints": {},
      "policies": {},
      "checkConstraints": {},
      "isRLSEnabled": false
    },
    "public.payload_locked_documents": {
      "name": "payload_locked_documents",
      "schema": "",
      "columns": {
        "id": {
          "name": "id",
          "type": "serial",
          "primaryKey": true,
          "notNull": true
        },
        "global_slug": {
          "name": "global_slug",
          "type": "varchar",
          "primaryKey": false,
          "notNull": false
        },
        "updated_at": {
          "name": "updated_at",
          "type": "timestamp(3) with time zone",
          "primaryKey": false,
          "notNull": true,
          "default": "now()"
        },
        "created_at": {
          "name": "created_at",
          "type": "timestamp(3) with time zone",
          "primaryKey": false,
          "notNull": true,
          "default": "now()"
        }
      },
      "indexes": {
        "payload_locked_documents_global_slug_idx": {
          "name": "payload_locked_documents_global_slug_idx",
          "columns": [
            {
              "expression": "global_slug",
              "isExpression": false,
              "asc": true,
              "nulls": "last"
            }
          ],
          "isUnique": false,
          "concurrently": false,
          "method": "btree",
          "with": {}
        },
        "payload_locked_documents_updated_at_idx": {
          "name": "payload_locked_documents_updated_at_idx",
          "columns": [
            {
              "expression": "updated_at",
              "isExpression": false,
              "asc": true,
              "nulls": "last"
            }
          ],
          "isUnique": false,
          "concurrently": false,
          "method": "btree",
          "with": {}
        },
        "payload_locked_documents_created_at_idx": {
          "name": "payload_locked_documents_created_at_idx",
          "columns": [
            {
              "expression": "created_at",
              "isExpression": false,
              "asc": true,
              "nulls": "last"
            }
          ],
          "isUnique": false,
          "concurrently": false,
          "method": "btree",
          "with": {}
        }
      },
      "foreignKeys": {},
      "compositePrimaryKeys": {},
      "uniqueConstraints": {},
      "policies": {},
      "checkConstraints": {},
      "isRLSEnabled": false
    },
    "public.payload_locked_documents_rels": {
      "name": "payload_locked_documents_rels",
      "schema": "",
      "columns": {
        "id": {
          "name": "id",
          "type": "serial",
          "primaryKey": true,
          "notNull": true
        },
        "order": {
          "name": "order",
          "type": "integer",
          "primaryKey": false,
          "notNull": false
        },
        "parent_id": {
          "name": "parent_id",
          "type": "integer",
          "primaryKey": false,
          "notNull": true
        },
        "path": {
          "name": "path",
          "type": "varchar",
          "primaryKey": false,
          "notNull": true
        },
        "users_id": {
          "name": "users_id",
          "type": "integer",
          "primaryKey": false,
          "notNull": false
        },
        "media_id": {
          "name": "media_id",
          "type": "integer",
          "primaryKey": false,
          "notNull": false
        },
        "services_id": {
          "name": "services_id",
          "type": "integer",
          "primaryKey": false,
          "notNull": false
        },
        "doc_versions_id": {
          "name": "doc_versions_id",
          "type": "integer",
          "primaryKey": false,
          "notNull": false
        },
        "doc_page_groups_id": {
          "name": "doc_page_groups_id",
          "type": "integer",
          "primaryKey": false,
          "notNull": false
        },
        "doc_pages_id": {
          "name": "doc_pages_id",
          "type": "integer",
          "primaryKey": false,
          "notNull": false
        },
        "redirects_id": {
          "name": "redirects_id",
          "type": "integer",
          "primaryKey": false,
          "notNull": false
        }
      },
      "indexes": {
        "payload_locked_documents_rels_order_idx": {
          "name": "payload_locked_documents_rels_order_idx",
          "columns": [
            {
              "expression": "order",
              "isExpression": false,
              "asc": true,
              "nulls": "last"
            }
          ],
          "isUnique": false,
          "concurrently": false,
          "method": "btree",
          "with": {}
        },
        "payload_locked_documents_rels_parent_idx": {
          "name": "payload_locked_documents_rels_parent_idx",
          "columns": [
            {
              "expression": "parent_id",
              "isExpression": false,
              "asc": true,
              "nulls": "last"
            }
          ],
          "isUnique": false,
          "concurrently": false,
          "method": "btree",
          "with": {}
        },
        "payload_locked_documents_rels_path_idx": {
          "name": "payload_locked_documents_rels_path_idx",
          "columns": [
            {
              "expression": "path",
              "isExpression": false,
              "asc": true,
              "nulls": "last"
            }
          ],
          "isUnique": false,
          "concurrently": false,
          "method": "btree",
          "with": {}
        },
        "payload_locked_documents_rels_users_id_idx": {
          "name": "payload_locked_documents_rels_users_id_idx",
          "columns": [
            {
              "expression": "users_id",
              "isExpression": false,
              "asc": true,
              "nulls": "last"
            }
          ],
          "isUnique": false,
          "concurrently": false,
          "method": "btree",
          "with": {}
        },
        "payload_locked_documents_rels_media_id_idx": {
          "name": "payload_locked_documents_rels_media_id_idx",
          "columns": [
            {
              "expression": "media_id",
              "isExpression": false,
              "asc": true,
              "nulls": "last"
            }
          ],
          "isUnique": false,
          "concurrently": false,
          "method": "btree",
          "with": {}
        },
        "payload_locked_documents_rels_services_id_idx": {
          "name": "payload_locked_documents_rels_services_id_idx",
          "columns": [
            {
              "expression": "services_id",
              "isExpression": false,
              "asc": true,
              "nulls": "last"
            }
          ],
          "isUnique": false,
          "concurrently": false,
          "method": "btree",
          "with": {}
        },
        "payload_locked_documents_rels_doc_versions_id_idx": {
          "name": "payload_locked_documents_rels_doc_versions_id_idx",
          "columns": [
            {
              "expression": "doc_versions_id",
              "isExpression": false,
              "asc": true,
              "nulls": "last"
            }
          ],
          "isUnique": false,
          "concurrently": false,
          "method": "btree",
          "with": {}
        },
        "payload_locked_documents_rels_doc_page_groups_id_idx": {
          "name": "payload_locked_documents_rels_doc_page_groups_id_idx",
          "columns": [
            {
              "expression": "doc_page_groups_id",
              "isExpression": false,
              "asc": true,
              "nulls": "last"
            }
          ],
          "isUnique": false,
          "concurrently": false,
          "method": "btree",
          "with": {}
        },
        "payload_locked_documents_rels_doc_pages_id_idx": {
          "name": "payload_locked_documents_rels_doc_pages_id_idx",
          "columns": [
            {
              "expression": "doc_pages_id",
              "isExpression": false,
              "asc": true,
              "nulls": "last"
            }
          ],
          "isUnique": false,
          "concurrently": false,
          "method": "btree",
          "with": {}
        },
        "payload_locked_documents_rels_redirects_id_idx": {
          "name": "payload_locked_documents_rels_redirects_id_idx",
          "columns": [
            {
              "expression": "redirects_id",
              "isExpression": false,
              "asc": true,
              "nulls": "last"
            }
          ],
          "isUnique": false,
          "concurrently": false,
          "method": "btree",
          "with": {}
        }
      },
      "foreignKeys": {
        "payload_locked_documents_rels_parent_fk": {
          "name": "payload_locked_documents_rels_parent_fk",
          "tableFrom": "payload_locked_documents_rels",
          "tableTo": "payload_locked_documents",
          "columnsFrom": [
            "parent_id"
          ],
          "columnsTo": [
            "id"
          ],
          "onDelete": "cascade",
          "onUpdate": "no action"
        },
        "payload_locked_documents_rels_users_fk": {
          "name": "payload_locked_documents_rels_users_fk",
          "tableFrom": "payload_locked_documents_rels",
          "tableTo": "users",
          "columnsFrom": [
            "users_id"
          ],
          "columnsTo": [
            "id"
          ],
          "onDelete": "cascade",
          "onUpdate": "no action"
        },
        "payload_locked_documents_rels_media_fk": {
          "name": "payload_locked_documents_rels_media_fk",
          "tableFrom": "payload_locked_documents_rels",
          "tableTo": "media",
          "columnsFrom": [
            "media_id"
          ],
          "columnsTo": [
            "id"
          ],
          "onDelete": "cascade",
          "onUpdate": "no action"
        },
        "payload_locked_documents_rels_services_fk": {
          "name": "payload_locked_documents_rels_services_fk",
          "tableFrom": "payload_locked_documents_rels",
          "tableTo": "services",
          "columnsFrom": [
            "services_id"
          ],
          "columnsTo": [
            "id"
          ],
          "onDelete": "cascade",
          "onUpdate": "no action"
        },
        "payload_locked_documents_rels_doc_versions_fk": {
          "name": "payload_locked_documents_rels_doc_versions_fk",
          "tableFrom": "payload_locked_documents_rels",
          "tableTo": "doc_versions",
          "columnsFrom": [
            "doc_versions_id"
          ],
          "columnsTo": [
            "id"
          ],
          "onDelete": "cascade",
          "onUpdate": "no action"
        },
        "payload_locked_documents_rels_doc_page_groups_fk": {
          "name": "payload_locked_documents_rels_doc_page_groups_fk",
          "tableFrom": "payload_locked_documents_rels",
          "tableTo": "doc_page_groups",
          "columnsFrom": [
            "doc_page_groups_id"
          ],
          "columnsTo": [
            "id"
          ],
          "onDelete": "cascade",
          "onUpdate": "no action"
        },
        "payload_locked_documents_rels_doc_pages_fk": {
          "name": "payload_locked_documents_rels_doc_pages_fk",
          "tableFrom": "payload_locked_documents_rels",
          "tableTo": "doc_pages",
          "columnsFrom": [
            "doc_pages_id"
          ],
          "columnsTo": [
            "id"
          ],
          "onDelete": "cascade",
          "onUpdate": "no action"
        },
        "payload_locked_documents_rels_redirects_fk": {
          "name": "payload_locked_documents_rels_redirects_fk",
          "tableFrom": "payload_locked_documents_rels",
          "tableTo": "redirects",
          "columnsFrom": [
            "redirects_id"
          ],
          "columnsTo": [
            "id"
          ],
          "onDelete": "cascade",
          "onUpdate": "no action"
        }
      },
      "compositePrimaryKeys": {},
      "uniqueConstraints": {},
      "policies": {},
      "checkConstraints": {},
      "isRLSEnabled": false
    },
    "public.payload_preferences": {
      "name": "payload_preferences",
      "schema": "",
      "columns": {
        "id": {
          "name": "id",
          "type": "serial",
          "primaryKey": true,
          "notNull": true
        },
        "key": {
          "name": "key",
          "type": "varchar",
          "primaryKey": false,
          "notNull": false
        },
        "value": {
          "name": "value",
          "type": "jsonb",
          "primaryKey": false,
          "notNull": false
        },
        "updated_at": {
          "name": "updated_at",
          "type": "timestamp(3) with time zone",
          "primaryKey": false,
          "notNull": true,
          "default": "now()"
        },
        "created_at": {
          "name": "created_at",
          "type": "timestamp(3) with time zone",
          "primaryKey": false,
          "notNull": true,
          "default": "now()"
        }
      },
      "indexes": {
        "payload_preferences_key_idx": {
          "name": "payload_preferences_key_idx",
          "columns": [
            {
              "expression": "key",
              "isExpression": false,
              "asc": true,
              "nulls": "last"
            }
          ],
          "isUnique": false,
          "concurrently": false,
          "method": "btree",
          "with": {}
        },
        "payload_preferences_updated_at_idx": {
          "name": "payload_preferences_updated_at_idx",
          "columns": [
            {
              "expression": "updated_at",
              "isExpression": false,
              "asc": true,
              "nulls": "last"
            }
          ],
          "isUnique": false,
          "concurrently": false,
          "method": "btree",
          "with": {}
        },
        "payload_preferences_created_at_idx": {
          "name": "payload_preferences_created_at_idx",
          "columns": [
            {
              "expression": "created_at",
              "isExpression": false,
              "asc": true,
              "nulls": "last"
            }
          ],
          "isUnique": false,
          "concurrently": false,
          "method": "btree",
          "with": {}
        }
      },
      "foreignKeys": {},
      "compositePrimaryKeys": {},
      "uniqueConstraints": {},
      "policies": {},
      "checkConstraints": {},
      "isRLSEnabled": false
    },
    "public.payload_preferences_rels": {
      "name": "payload_preferences_rels",
      "schema": "",
      "columns": {
        "id": {
          "name": "id",
          "type": "serial",
          "primaryKey": true,
          "notNull": true
        },
        "order": {
          "name": "order",
          "type": "integer",
          "primaryKey": false,
          "notNull": false
        },
        "parent_id": {
          "name": "parent_id",
          "type": "integer",
          "primaryKey": false,
          "notNull": true
        },
        "path": {
          "name": "path",
          "type": "varchar",
          "primaryKey": false,
          "notNull": true
        },
        "users_id": {
          "name": "users_id",
          "type": "integer",
          "primaryKey": false,
          "notNull": false
        }
      },
      "indexes": {
        "payload_preferences_rels_order_idx": {
          "name": "payload_preferences_rels_order_idx",
          "columns": [
            {
              "expression": "order",
              "isExpression": false,
              "asc": true,
              "nulls": "last"
            }
          ],
          "isUnique": false,
          "concurrently": false,
          "method": "btree",
          "with": {}
        },
        "payload_preferences_rels_parent_idx": {
          "name": "payload_preferences_rels_parent_idx",
          "columns": [
            {
              "expression": "parent_id",
              "isExpression": false,
              "asc": true,
              "nulls": "last"
            }
          ],
          "isUnique": false,
          "concurrently": false,
          "method": "btree",
          "with": {}
        },
        "payload_preferences_rels_path_idx": {
          "name": "payload_preferences_rels_path_idx",
          "columns": [
            {
              "expression": "path",
              "isExpression": false,
              "asc": true,
              "nulls": "last"
            }
          ],
          "isUnique": false,
          "concurrently": false,
          "method": "btree",
          "with": {}
        },
        "payload_preferences_rels_users_id_idx": {
          "name": "payload_preferences_rels_users_id_idx",
          "columns": [
            {
              "expression": "users_id",
              "isExpression": false,
              "asc": true,
              "nulls": "last"
            }
          ],
          "isUnique": false,
          "concurrently": false,
          "method": "btree",
          "with": {}
        }
      },
      "foreignKeys": {
        "payload_preferences_rels_parent_fk": {
          "name": "payload_preferences_rels_parent_fk",
          "tableFrom": "payload_preferences_rels",
          "tableTo": "payload_preferences",
          "columnsFrom": [
            "parent_id"
          ],
          "columnsTo": [
            "id"
          ],
          "onDelete": "cascade",
          "onUpdate": "no action"
        },
        "payload_preferences_rels_users_fk": {
          "name": "payload_preferences_rels_users_fk",
          "tableFrom": "payload_preferences_rels",
          "tableTo": "users",
          "columnsFrom": [
            "users_id"
          ],
          "columnsTo": [
            "id"
          ],
          "onDelete": "cascade",
          "onUpdate": "no action"
        }
      },
      "compositePrimaryKeys": {},
      "uniqueConstraints": {},
      "policies": {},
      "checkConstraints": {},
      "isRLSEnabled": false
    },
    "public.payload_migrations": {
      "name": "payload_migrations",
      "schema": "",
      "columns": {
        "id": {
          "name": "id",
          "type": "serial",
          "primaryKey": true,
          "notNull": true
        },
        "name": {
          "name": "name",
          "type": "varchar",
          "primaryKey": false,
          "notNull": false
        },
        "batch": {
          "name": "batch",
          "type": "numeric",
          "primaryKey": false,
          "notNull": false
        },
        "updated_at": {
          "name": "updated_at",
          "type": "timestamp(3) with time zone",
          "primaryKey": false,
          "notNull": true,
          "default": "now()"
        },
        "created_at": {
          "name": "created_at",
          "type": "timestamp(3) with time zone",
          "primaryKey": false,
          "notNull": true,
          "default": "now()"
        }
      },
      "indexes": {
        "payload_migrations_updated_at_idx": {
          "name": "payload_migrations_updated_at_idx",
          "columns": [
            {
              "expression": "updated_at",
              "isExpression": false,
              "asc": true,
              "nulls": "last"
            }
          ],
          "isUnique": false,
          "concurrently": false,
          "method": "btree",
          "with": {}
        },
        "payload_migrations_created_at_idx": {
          "name": "payload_migrations_created_at_idx",
          "columns": [
            {
              "expression": "created_at",
              "isExpression": false,
              "asc": true,
              "nulls": "last"
            }
          ],
          "isUnique": false,
          "concurrently": false,
          "method": "btree",
          "with": {}
        }
      },
      "foreignKeys": {},
      "compositePrimaryKeys": {},
      "uniqueConstraints": {},
      "policies": {},
      "checkConstraints": {},
      "isRLSEnabled": false
    },
    "public.docs_settings": {
      "name": "docs_settings",
      "schema": "",
      "columns": {
        "id": {
          "name": "id",
          "type": "serial",
          "primaryKey": true,
          "notNull": true
        },
        "home_title": {
          "name": "home_title",
          "type": "varchar",
          "primaryKey": false,
          "notNull": false
        },
        "home_description": {
          "name": "home_description",
          "type": "varchar",
          "primaryKey": false,
          "notNull": false
        },
        "home_content": {
          "name": "home_content",
          "type": "jsonb",
          "primaryKey": false,
          "notNull": true
        },
        "updated_at": {
          "name": "updated_at",
          "type": "timestamp(3) with time zone",
          "primaryKey": false,
          "notNull": false
        },
        "created_at": {
          "name": "created_at",
          "type": "timestamp(3) with time zone",
          "primaryKey": false,
          "notNull": false
        }
      },
      "indexes": {},
      "foreignKeys": {},
      "compositePrimaryKeys": {},
      "uniqueConstraints": {},
      "policies": {},
      "checkConstraints": {},
      "isRLSEnabled": false
    }
  },
  "enums": {
    "public.enum_users_roles": {
      "name": "enum_users_roles",
      "schema": "public",
      "values": [
        "writer",
        "editor",
        "admin"
      ]
    },
    "public.enum_services_icon_source": {
      "name": "enum_services_icon_source",
      "schema": "public",
      "values": [
        "lucide",
        "custom"
      ]
    },
    "public.enum_services_icon_lucide": {
      "name": "enum_services_icon_lucide",
      "schema": "public",
      "values": [
        "AArrowDown",
        "AArrowUp",
        "Accessibility",
        "Activity",
        "Airplay",
        "AirVent",
        "ALargeSmall",
        "AlarmClock",
        "AlarmClockCheck",
        "AlarmClockMinus",
        "AlarmClockOff",
        "AlarmClockPlus",
        "AlarmSmoke",
        "Album",
        "AlignCenterHorizontal",
        "AlignCenterVertical",
        "AlignEndHorizontal",
        "AlignEndVertical",
        "AlignHorizontalDistributeCenter",
        "AlignHorizontalDistributeEnd",
        "AlignHorizontalDistributeStart",
        "AlignHorizontalJustifyCenter",
        "AlignHorizontalJustifyEnd",
        "AlignHorizontalJustifyStart",
        "AlignHorizontalSpaceAround",
        "AlignHorizontalSpaceBetween",
        "AlignStartHorizontal",
        "AlignStartVertical",
        "AlignVerticalDistributeCenter",
        "AlignVerticalDistributeEnd",
        "AlignVerticalDistributeStart",
        "AlignVerticalJustifyCenter",
        "AlignVerticalJustifyEnd",
        "AlignVerticalJustifyStart",
        "AlignVerticalSpaceAround",
        "AlignVerticalSpaceBetween",
        "Ambulance",
        "Ampersand",
        "Ampersands",
        "Amphora",
        "Anchor",
        "Angry",
        "Annoyed",
        "Antenna",
        "Anvil",
        "Aperture",
        "Apple",
        "AppWindow",
        "AppWindowMac",
        "Archive",
        "ArchiveRestore",
        "ArchiveX",
        "Armchair",
        "ArrowBigDown",
        "ArrowBigDownDash",
        "ArrowBigLeft",
        "ArrowBigLeftDash",
        "ArrowBigRight",
        "ArrowBigRightDash",
        "ArrowBigUp",
        "ArrowBigUpDash",
        "ArrowDown",
        "ArrowDown01",
        "ArrowDown10",
        "ArrowDownAZ",
        "ArrowDownFromLine",
        "ArrowDownLeft",
        "ArrowDownNarrowWide",
        "ArrowDownRight",
        "ArrowDownToDot",
        "ArrowDownToLine",
        "ArrowDownUp",
        "ArrowDownWideNarrow",
        "ArrowDownZA",
        "ArrowLeft",
        "ArrowLeftFromLine",
        "ArrowLeftRight",
        "ArrowLeftToLine",
        "ArrowRight",
        "ArrowRightFromLine",
        "ArrowRightLeft",
        "ArrowRightToLine",
        "ArrowsUpFromLine",
        "ArrowUp",
        "ArrowUp01",
        "ArrowUp10",
        "ArrowUpAZ",
        "ArrowUpDown",
        "ArrowUpFromDot",
        "ArrowUpFromLine",
        "ArrowUpLeft",
        "ArrowUpNarrowWide",
        "ArrowUpRight",
        "ArrowUpToLine",
        "ArrowUpWideNarrow",
        "ArrowUpZA",
        "Asterisk",
        "Atom",
        "AtSign",
        "AudioLines",
        "AudioWaveform",
        "Award",
        "Axe",
        "Axis3d",
        "Baby",
        "Backpack",
        "Badge",
        "BadgeAlert",
        "BadgeCent",
        "BadgeCheck",
        "BadgeDollarSign",
        "BadgeEuro",
        "BadgeIndianRupee",
        "BadgeInfo",
        "BadgeJapaneseYen",
        "BadgeMinus",
        "BadgePercent",
        "BadgePlus",
        "BadgePoundSterling",
        "BadgeQuestionMark",
        "BadgeRussianRuble",
        "BadgeSwissFranc",
        "BadgeTurkishLira",
        "BadgeX",
        "BaggageClaim",
        "Balloon",
        "Ban",
        "Banana",
        "Bandage",
        "Banknote",
        "BanknoteArrowDown",
        "BanknoteArrowUp",
        "BanknoteX",
        "Barcode",
        "Barrel",
        "Baseline",
        "Bath",
        "Battery",
        "BatteryCharging",
        "BatteryFull",
        "BatteryLow",
        "BatteryMedium",
        "BatteryPlus",
        "BatteryWarning",
        "Beaker",
        "Bean",
        "BeanOff",
        "Bed",
        "BedDouble",
        "BedSingle",
        "Beef",
        "Beer",
        "BeerOff",
        "Bell",
        "BellDot",
        "BellElectric",
        "BellMinus",
        "BellOff",
        "BellPlus",
        "BellRing",
        "BetweenHorizontalEnd",
        "BetweenHorizontalStart",
        "BetweenVerticalEnd",
        "BetweenVerticalStart",
        "BicepsFlexed",
        "Bike",
        "Binary",
        "Binoculars",
        "Biohazard",
        "Bird",
        "Birdhouse",
        "Bitcoin",
        "Blend",
        "Blinds",
        "Blocks",
        "Bluetooth",
        "BluetoothConnected",
        "BluetoothOff",
        "BluetoothSearching",
        "Bold",
        "Bolt",
        "Bomb",
        "Bone",
        "Book",
        "BookA",
        "BookAlert",
        "BookAudio",
        "BookCheck",
        "BookCopy",
        "BookDashed",
        "BookDown",
        "BookHeadphones",
        "BookHeart",
        "BookImage",
        "BookKey",
        "BookLock",
        "Bookmark",
        "BookmarkCheck",
        "BookMarked",
        "BookmarkMinus",
        "BookmarkPlus",
        "BookmarkX",
        "BookMinus",
        "BookOpen",
        "BookOpenCheck",
        "BookOpenText",
        "BookPlus",
        "BookSearch",
        "BookText",
        "BookType",
        "BookUp",
        "BookUp2",
        "BookUser",
        "BookX",
        "BoomBox",
        "Bot",
        "BotMessageSquare",
        "BotOff",
        "BottleWine",
        "BowArrow",
        "Box",
        "Boxes",
        "Braces",
        "Brackets",
        "Brain",
        "BrainCircuit",
        "BrainCog",
        "BrickWall",
        "BrickWallFire",
        "BrickWallShield",
        "Briefcase",
        "BriefcaseBusiness",
        "BriefcaseConveyorBelt",
        "BriefcaseMedical",
        "BringToFront",
        "Brush",
        "BrushCleaning",
        "Bubbles",
        "Bug",
        "BugOff",
        "BugPlay",
        "Building",
        "Building2",
        "Bus",
        "BusFront",
        "Cable",
        "CableCar",
        "Cake",
        "CakeSlice",
        "Calculator",
        "Calendar",
        "Calendar1",
        "CalendarArrowDown",
        "CalendarArrowUp",
        "CalendarCheck",
        "CalendarCheck2",
        "CalendarClock",
        "CalendarCog",
        "CalendarDays",
        "CalendarFold",
        "CalendarHeart",
        "CalendarMinus",
        "CalendarMinus2",
        "CalendarOff",
        "CalendarPlus",
        "CalendarPlus2",
        "CalendarRange",
        "Calendars",
        "CalendarSearch",
        "CalendarSync",
        "CalendarX",
        "CalendarX2",
        "Camera",
        "CameraOff",
        "Candy",
        "CandyCane",
        "CandyOff",
        "Cannabis",
        "CannabisOff",
        "Captions",
        "CaptionsOff",
        "Car",
        "Caravan",
        "CardSim",
        "CarFront",
        "Carrot",
        "CarTaxiFront",
        "CaseLower",
        "CaseSensitive",
        "CaseUpper",
        "CassetteTape",
        "Cast",
        "Castle",
        "Cat",
        "Cctv",
        "ChartArea",
        "ChartBar",
        "ChartBarBig",
        "ChartBarDecreasing",
        "ChartBarIncreasing",
        "ChartBarStacked",
        "ChartCandlestick",
        "ChartColumn",
        "ChartColumnBig",
        "ChartColumnDecreasing",
        "ChartColumnIncreasing",
        "ChartColumnStacked",
        "ChartGantt",
        "ChartLine",
        "ChartNetwork",
        "ChartNoAxesColumn",
        "ChartNoAxesColumnDecreasing",
        "ChartNoAxesColumnIncreasing",
        "ChartNoAxesCombined",
        "ChartNoAxesGantt",
        "ChartPie",
        "ChartScatter",
        "ChartSpline",
        "Check",
        "CheckCheck",
        "CheckLine",
        "ChefHat",
        "Cherry",
        "ChessBishop",
        "ChessKing",
        "ChessKnight",
        "ChessPawn",
        "ChessQueen",
        "ChessRook",
        "ChevronDown",
        "ChevronFirst",
        "ChevronLast",
        "ChevronLeft",
        "ChevronRight",
        "ChevronsDown",
        "ChevronsDownUp",
        "ChevronsLeft",
        "ChevronsLeftRight",
        "ChevronsLeftRightEllipsis",
        "ChevronsRight",
        "ChevronsRightLeft",
        "ChevronsUp",
        "ChevronsUpDown",
        "ChevronUp",
        "Chromium",
        "Church",
        "Cigarette",
        "CigaretteOff",
        "Circle",
        "CircleAlert",
        "CircleArrowDown",
        "CircleArrowLeft",
        "CircleArrowOutDownLeft",
        "CircleArrowOutDownRight",
        "CircleArrowOutUpLeft",
        "CircleArrowOutUpRight",
        "CircleArrowRight",
        "CircleArrowUp",
        "CircleCheck",
        "CircleCheckBig",
        "CircleChevronDown",
        "CircleChevronLeft",
        "CircleChevronRight",
        "CircleChevronUp",
        "CircleDashed",
        "CircleDivide",
        "CircleDollarSign",
        "CircleDot",
        "CircleDotDashed",
        "CircleEllipsis",
        "CircleEqual",
        "CircleFadingArrowUp",
        "CircleFadingPlus",
        "CircleGauge",
        "CircleMinus",
        "CircleOff",
        "CircleParking",
        "CircleParkingOff",
        "CirclePause",
        "CirclePercent",
        "CirclePile",
        "CirclePlay",
        "CirclePlus",
        "CirclePoundSterling",
        "CirclePower",
        "CircleQuestionMark",
        "CircleSlash",
        "CircleSlash2",
        "CircleSmall",
        "CircleStar",
        "CircleStop",
        "CircleUser",
        "CircleUserRound",
        "CircleX",
        "CircuitBoard",
        "Citrus",
        "Clapperboard",
        "Clipboard",
        "ClipboardCheck",
        "ClipboardClock",
        "ClipboardCopy",
        "ClipboardList",
        "ClipboardMinus",
        "ClipboardPaste",
        "ClipboardPen",
        "ClipboardPenLine",
        "ClipboardPlus",
        "ClipboardType",
        "ClipboardX",
        "Clock",
        "Clock1",
        "Clock10",
        "Clock11",
        "Clock12",
        "Clock2",
        "Clock3",
        "Clock4",
        "Clock5",
        "Clock6",
        "Clock7",
        "Clock8",
        "Clock9",
        "ClockAlert",
        "ClockArrowDown",
        "ClockArrowUp",
        "ClockCheck",
        "ClockFading",
        "ClockPlus",
        "ClosedCaption",
        "Cloud",
        "CloudAlert",
        "CloudBackup",
        "CloudCheck",
        "CloudCog",
        "CloudDownload",
        "CloudDrizzle",
        "CloudFog",
        "CloudHail",
        "CloudLightning",
        "CloudMoon",
        "CloudMoonRain",
        "CloudOff",
        "CloudRain",
        "CloudRainWind",
        "CloudSnow",
        "CloudSun",
        "CloudSunRain",
        "CloudSync",
        "CloudUpload",
        "Cloudy",
        "Clover",
        "Club",
        "Code",
        "Codepen",
        "Codesandbox",
        "CodeXml",
        "Coffee",
        "Cog",
        "Coins",
        "Columns2",
        "Columns3",
        "Columns3Cog",
        "Columns4",
        "Combine",
        "Command",
        "Compass",
        "Component",
        "Computer",
        "ConciergeBell",
        "Cone",
        "Construction",
        "Contact",
        "ContactRound",
        "Container",
        "Contrast",
        "Cookie",
        "CookingPot",
        "Copy",
        "CopyCheck",
        "Copyleft",
        "CopyMinus",
        "CopyPlus",
        "Copyright",
        "CopySlash",
        "CopyX",
        "CornerDownLeft",
        "CornerDownRight",
        "CornerLeftDown",
        "CornerLeftUp",
        "CornerRightDown",
        "CornerRightUp",
        "CornerUpLeft",
        "CornerUpRight",
        "Cpu",
        "CreativeCommons",
        "CreditCard",
        "Croissant",
        "Crop",
        "Cross",
        "Crosshair",
        "Crown",
        "Cuboid",
        "CupSoda",
        "Currency",
        "Cylinder",
        "Dam",
        "Database",
        "DatabaseBackup",
        "DatabaseZap",
        "DecimalsArrowLeft",
        "DecimalsArrowRight",
        "Delete",
        "Dessert",
        "Diameter",
        "Diamond",
        "DiamondMinus",
        "DiamondPercent",
        "DiamondPlus",
        "Dice1",
        "Dice2",
        "Dice3",
        "Dice4",
        "Dice5",
        "Dice6",
        "Dices",
        "Diff",
        "Disc",
        "Disc2",
        "Disc3",
        "DiscAlbum",
        "Divide",
        "Dna",
        "DnaOff",
        "Dock",
        "Dog",
        "DollarSign",
        "Donut",
        "DoorClosed",
        "DoorClosedLocked",
        "DoorOpen",
        "Dot",
        "Download",
        "DraftingCompass",
        "Drama",
        "Dribbble",
        "Drill",
        "Drone",
        "Droplet",
        "DropletOff",
        "Droplets",
        "Drum",
        "Drumstick",
        "Dumbbell",
        "Ear",
        "EarOff",
        "Earth",
        "EarthLock",
        "Eclipse",
        "Egg",
        "EggFried",
        "EggOff",
        "Ellipsis",
        "EllipsisVertical",
        "Equal",
        "EqualApproximately",
        "EqualNot",
        "Eraser",
        "EthernetPort",
        "Euro",
        "EvCharger",
        "Expand",
        "ExternalLink",
        "Eye",
        "EyeClosed",
        "EyeOff",
        "Facebook",
        "Factory",
        "Fan",
        "FastForward",
        "Feather",
        "Fence",
        "FerrisWheel",
        "Figma",
        "File",
        "FileArchive",
        "FileAxis3d",
        "FileBadge",
        "FileBox",
        "FileBraces",
        "FileBracesCorner",
        "FileChartColumn",
        "FileChartColumnIncreasing",
        "FileChartLine",
        "FileChartPie",
        "FileCheck",
        "FileCheckCorner",
        "FileClock",
        "FileCode",
        "FileCodeCorner",
        "FileCog",
        "FileDiff",
        "FileDigit",
        "FileDown",
        "FileExclamationPoint",
        "FileHeadphone",
        "FileHeart",
        "FileImage",
        "FileInput",
        "FileKey",
        "FileLock",
        "FileMinus",
        "FileMinusCorner",
        "FileMusic",
        "FileOutput",
        "FilePen",
        "FilePenLine",
        "FilePlay",
        "FilePlus",
        "FilePlusCorner",
        "FileQuestionMark",
        "Files",
        "FileScan",
        "FileSearch",
        "FileSearchCorner",
        "FileSignal",
        "FileSliders",
        "FileSpreadsheet",
        "FileStack",
        "FileSymlink",
        "FileTerminal",
        "FileText",
        "FileType",
        "FileTypeCorner",
        "FileUp",
        "FileUser",
        "FileVideoCamera",
        "FileVolume",
        "FileX",
        "FileXCorner",
        "Film",
        "FingerprintPattern",
        "FireExtinguisher",
        "Fish",
        "FishingHook",
        "FishOff",
        "FishSymbol",
        "Flag",
        "FlagOff",
        "FlagTriangleLeft",
        "FlagTriangleRight",
        "Flame",
        "FlameKindling",
        "Flashlight",
        "FlashlightOff",
        "FlaskConical",
        "FlaskConicalOff",
        "FlaskRound",
        "FlipHorizontal",
        "FlipHorizontal2",
        "FlipVertical",
        "FlipVertical2",
        "Flower",
        "Flower2",
        "Focus",
        "Folder",
        "FolderArchive",
        "FolderCheck",
        "FolderClock",
        "FolderClosed",
        "FolderCode",
        "FolderCog",
        "FolderDot",
        "FolderDown",
        "FolderGit",
        "FolderGit2",
        "FolderHeart",
        "FolderInput",
        "FolderKanban",
        "FolderKey",
        "FolderLock",
        "FolderMinus",
        "FolderOpen",
        "FolderOpenDot",
        "FolderOutput",
        "FolderPen",
        "FolderPlus",
        "FolderRoot",
        "Folders",
        "FolderSearch",
        "FolderSearch2",
        "FolderSymlink",
        "FolderSync",
        "FolderTree",
        "FolderUp",
        "FolderX",
        "FoldHorizontal",
        "FoldVertical",
        "Footprints",
        "Forklift",
        "Form",
        "Forward",
        "Frame",
        "Framer",
        "Frown",
        "Fuel",
        "Fullscreen",
        "Funnel",
        "FunnelPlus",
        "FunnelX",
        "GalleryHorizontal",
        "GalleryHorizontalEnd",
        "GalleryThumbnails",
        "GalleryVertical",
        "GalleryVerticalEnd",
        "Gamepad",
        "Gamepad2",
        "GamepadDirectional",
        "Gauge",
        "Gavel",
        "Gem",
        "GeorgianLari",
        "Ghost",
        "Gift",
        "GitBranch",
        "GitBranchMinus",
        "GitBranchPlus",
        "GitCommitHorizontal",
        "GitCommitVertical",
        "GitCompare",
        "GitCompareArrows",
        "GitFork",
        "GitGraph",
        "Github",
        "Gitlab",
        "GitMerge",
        "GitPullRequest",
        "GitPullRequestArrow",
        "GitPullRequestClosed",
        "GitPullRequestCreate",
        "GitPullRequestCreateArrow",
        "GitPullRequestDraft",
        "Glasses",
        "GlassWater",
        "Globe",
        "GlobeLock",
        "GlobeX",
        "Goal",
        "Gpu",
        "GraduationCap",
        "Grape",
        "Grid2x2",
        "Grid2x2Check",
        "Grid2x2Plus",
        "Grid2x2X",
        "Grid3x2",
        "Grid3x3",
        "Grip",
        "GripHorizontal",
        "GripVertical",
        "Group",
        "Guitar",
        "Ham",
        "Hamburger",
        "Hammer",
        "Hand",
        "Handbag",
        "HandCoins",
        "HandFist",
        "HandGrab",
        "HandHeart",
        "HandHelping",
        "HandMetal",
        "HandPlatter",
        "Handshake",
        "HardDrive",
        "HardDriveDownload",
        "HardDriveUpload",
        "HardHat",
        "Hash",
        "HatGlasses",
        "Haze",
        "Hd",
        "HdmiPort",
        "Heading",
        "Heading1",
        "Heading2",
        "Heading3",
        "Heading4",
        "Heading5",
        "Heading6",
        "HeadphoneOff",
        "Headphones",
        "Headset",
        "Heart",
        "HeartCrack",
        "HeartHandshake",
        "HeartMinus",
        "HeartOff",
        "HeartPlus",
        "HeartPulse",
        "Heater",
        "Helicopter",
        "Hexagon",
        "Highlighter",
        "History",
        "Hop",
        "HopOff",
        "Hospital",
        "Hotel",
        "Hourglass",
        "House",
        "HouseHeart",
        "HousePlug",
        "HousePlus",
        "HouseWifi",
        "IceCreamBowl",
        "IceCreamCone",
        "IdCard",
        "IdCardLanyard",
        "Image",
        "ImageDown",
        "ImageMinus",
        "ImageOff",
        "ImagePlay",
        "ImagePlus",
        "Images",
        "ImageUp",
        "ImageUpscale",
        "Import",
        "Inbox",
        "IndianRupee",
        "Infinity",
        "Info",
        "InspectionPanel",
        "Instagram",
        "Italic",
        "IterationCcw",
        "IterationCw",
        "JapaneseYen",
        "Joystick",
        "Kanban",
        "Kayak",
        "Key",
        "Keyboard",
        "KeyboardMusic",
        "KeyboardOff",
        "KeyRound",
        "KeySquare",
        "Lamp",
        "LampCeiling",
        "LampDesk",
        "LampFloor",
        "LampWallDown",
        "LampWallUp",
        "Landmark",
        "LandPlot",
        "Languages",
        "Laptop",
        "LaptopMinimal",
        "LaptopMinimalCheck",
        "Lasso",
        "LassoSelect",
        "Laugh",
        "Layers",
        "Layers2",
        "LayersPlus",
        "LayoutDashboard",
        "LayoutGrid",
        "LayoutList",
        "LayoutPanelLeft",
        "LayoutPanelTop",
        "LayoutTemplate",
        "Leaf",
        "LeafyGreen",
        "Lectern",
        "Library",
        "LibraryBig",
        "LifeBuoy",
        "Ligature",
        "Lightbulb",
        "LightbulbOff",
        "LineSquiggle",
        "Link",
        "Link2",
        "Link2Off",
        "Linkedin",
        "List",
        "ListCheck",
        "ListChecks",
        "ListChevronsDownUp",
        "ListChevronsUpDown",
        "ListCollapse",
        "ListEnd",
        "ListFilter",
        "ListFilterPlus",
        "ListIndentDecrease",
        "ListIndentIncrease",
        "ListMinus",
        "ListMusic",
        "ListOrdered",
        "ListPlus",
        "ListRestart",
        "ListStart",
        "ListTodo",
        "ListTree",
        "ListVideo",
        "ListX",
        "Loader",
        "LoaderCircle",
        "LoaderPinwheel",
        "Locate",
        "LocateFixed",
        "LocateOff",
        "Lock",
        "LockKeyhole",
        "LockKeyholeOpen",
        "LockOpen",
        "LogIn",
        "LogOut",
        "Logs",
        "Lollipop",
        "Luggage",
        "Magnet",
        "Mail",
        "Mailbox",
        "MailCheck",
        "MailMinus",
        "MailOpen",
        "MailPlus",
        "MailQuestionMark",
        "Mails",
        "MailSearch",
        "MailWarning",
        "MailX",
        "Map",
        "MapMinus",
        "MapPin",
        "MapPinCheck",
        "MapPinCheckInside",
        "MapPinHouse",
        "MapPinMinus",
        "MapPinMinusInside",
        "MapPinned",
        "MapPinOff",
        "MapPinPen",
        "MapPinPlus",
        "MapPinPlusInside",
        "MapPinX",
        "MapPinXInside",
        "MapPlus",
        "Mars",
        "MarsStroke",
        "Martini",
        "Maximize",
        "Maximize2",
        "Medal",
        "Megaphone",
        "MegaphoneOff",
        "Meh",
        "MemoryStick",
        "Menu",
        "Merge",
        "MessageCircle",
        "MessageCircleCode",
        "MessageCircleDashed",
        "MessageCircleHeart",
        "MessageCircleMore",
        "MessageCircleOff",
        "MessageCirclePlus",
        "MessageCircleQuestionMark",
        "MessageCircleReply",
        "MessageCircleWarning",
        "MessageCircleX",
        "MessageSquare",
        "MessageSquareCode",
        "MessageSquareDashed",
        "MessageSquareDiff",
        "MessageSquareDot",
        "MessageSquareHeart",
        "MessageSquareLock",
        "MessageSquareMore",
        "MessageSquareOff",
        "MessageSquarePlus",
        "MessageSquareQuote",
        "MessageSquareReply",
        "MessageSquareShare",
        "MessageSquareText",
        "MessageSquareWarning",
        "MessageSquareX",
        "MessagesSquare",
        "Mic",
        "MicOff",
        "Microchip",
        "Microscope",
        "Microwave",
        "MicVocal",
        "Milestone",
        "Milk",
        "MilkOff",
        "Minimize",
        "Minimize2",
        "Minus",
        "Monitor",
        "MonitorCheck",
        "MonitorCloud",
        "MonitorCog",
        "MonitorDot",
        "MonitorDown",
        "MonitorOff",
        "MonitorPause",
        "MonitorPlay",
        "MonitorSmartphone",
        "MonitorSpeaker",
        "MonitorStop",
        "MonitorUp",
        "MonitorX",
        "Moon",
        "MoonStar",
        "Motorbike",
        "Mountain",
        "MountainSnow",
        "Mouse",
        "MouseOff",
        "MousePointer",
        "MousePointer2",
        "MousePointer2Off",
        "MousePointerBan",
        "MousePointerClick",
        "Move",
        "Move3d",
        "MoveDiagonal",
        "MoveDiagonal2",
        "MoveDown",
        "MoveDownLeft",
        "MoveDownRight",
        "MoveHorizontal",
        "MoveLeft",
        "MoveRight",
        "MoveUp",
        "MoveUpLeft",
        "MoveUpRight",
        "MoveVertical",
        "Music",
        "Music2",
        "Music3",
        "Music4",
        "Navigation",
        "Navigation2",
        "Navigation2Off",
        "NavigationOff",
        "Network",
        "Newspaper",
        "Nfc",
        "NonBinary",
        "Notebook",
        "NotebookPen",
        "NotebookTabs",
        "NotebookText",
        "NotepadText",
        "NotepadTextDashed",
        "Nut",
        "NutOff",
        "Octagon",
        "OctagonAlert",
        "OctagonMinus",
        "OctagonPause",
        "OctagonX",
        "Omega",
        "Option",
        "Orbit",
        "Origami",
        "Package",
        "Package2",
        "PackageCheck",
        "PackageMinus",
        "PackageOpen",
        "PackagePlus",
        "PackageSearch",
        "PackageX",
        "Paintbrush",
        "PaintbrushVertical",
        "PaintBucket",
        "PaintRoller",
        "Palette",
        "Panda",
        "PanelBottom",
        "PanelBottomClose",
        "PanelBottomDashed",
        "PanelBottomOpen",
        "PanelLeft",
        "PanelLeftClose",
        "PanelLeftDashed",
        "PanelLeftOpen",
        "PanelLeftRightDashed",
        "PanelRight",
        "PanelRightClose",
        "PanelRightDashed",
        "PanelRightOpen",
        "PanelsLeftBottom",
        "PanelsRightBottom",
        "PanelsTopLeft",
        "PanelTop",
        "PanelTopBottomDashed",
        "PanelTopClose",
        "PanelTopDashed",
        "PanelTopOpen",
        "Paperclip",
        "Parentheses",
        "ParkingMeter",
        "PartyPopper",
        "Pause",
        "PawPrint",
        "PcCase",
        "Pen",
        "Pencil",
        "PencilLine",
        "PencilOff",
        "PencilRuler",
        "PenLine",
        "PenOff",
        "Pentagon",
        "PenTool",
        "Percent",
        "PersonStanding",
        "PhilippinePeso",
        "Phone",
        "PhoneCall",
        "PhoneForwarded",
        "PhoneIncoming",
        "PhoneMissed",
        "PhoneOff",
        "PhoneOutgoing",
        "Pi",
        "Piano",
        "Pickaxe",
        "PictureInPicture",
        "PictureInPicture2",
        "PiggyBank",
        "Pilcrow",
        "PilcrowLeft",
        "PilcrowRight",
        "Pill",
        "PillBottle",
        "Pin",
        "PinOff",
        "Pipette",
        "Pizza",
        "Plane",
        "PlaneLanding",
        "PlaneTakeoff",
        "Play",
        "Plug",
        "Plug2",
        "PlugZap",
        "Plus",
        "Pocket",
        "PocketKnife",
        "Podcast",
        "Pointer",
        "PointerOff",
        "Popcorn",
        "Popsicle",
        "PoundSterling",
        "Power",
        "PowerOff",
        "Presentation",
        "Printer",
        "PrinterCheck",
        "PrinterX",
        "Projector",
        "Proportions",
        "Puzzle",
        "Pyramid",
        "QrCode",
        "Quote",
        "Rabbit",
        "Radar",
        "Radiation",
        "Radical",
        "Radio",
        "RadioReceiver",
        "RadioTower",
        "Radius",
        "RailSymbol",
        "Rainbow",
        "Rat",
        "Ratio",
        "Receipt",
        "ReceiptCent",
        "ReceiptEuro",
        "ReceiptIndianRupee",
        "ReceiptJapaneseYen",
        "ReceiptPoundSterling",
        "ReceiptRussianRuble",
        "ReceiptSwissFranc",
        "ReceiptText",
        "ReceiptTurkishLira",
        "RectangleCircle",
        "RectangleEllipsis",
        "RectangleGoggles",
        "RectangleHorizontal",
        "RectangleVertical",
        "Recycle",
        "Redo",
        "Redo2",
        "RedoDot",
        "RefreshCcw",
        "RefreshCcwDot",
        "RefreshCw",
        "RefreshCwOff",
        "Refrigerator",
        "Regex",
        "RemoveFormatting",
        "Repeat",
        "Repeat1",
        "Repeat2",
        "Replace",
        "ReplaceAll",
        "Reply",
        "ReplyAll",
        "Rewind",
        "Ribbon",
        "Rocket",
        "RockingChair",
        "RollerCoaster",
        "Rose",
        "Rotate3d",
        "RotateCcw",
        "RotateCcwKey",
        "RotateCcwSquare",
        "RotateCw",
        "RotateCwSquare",
        "Route",
        "RouteOff",
        "Router",
        "Rows2",
        "Rows3",
        "Rows4",
        "Rss",
        "Ruler",
        "RulerDimensionLine",
        "RussianRuble",
        "Sailboat",
        "Salad",
        "Sandwich",
        "Satellite",
        "SatelliteDish",
        "SaudiRiyal",
        "Save",
        "SaveAll",
        "SaveOff",
        "Scale",
        "Scale3d",
        "Scaling",
        "Scan",
        "ScanBarcode",
        "ScanEye",
        "ScanFace",
        "ScanHeart",
        "ScanLine",
        "ScanQrCode",
        "ScanSearch",
        "ScanText",
        "School",
        "Scissors",
        "ScissorsLineDashed",
        "Scooter",
        "ScreenShare",
        "ScreenShareOff",
        "Scroll",
        "ScrollText",
        "Search",
        "SearchAlert",
        "SearchCheck",
        "SearchCode",
        "SearchSlash",
        "SearchX",
        "Section",
        "Send",
        "SendHorizontal",
        "SendToBack",
        "SeparatorHorizontal",
        "SeparatorVertical",
        "Server",
        "ServerCog",
        "ServerCrash",
        "ServerOff",
        "Settings",
        "Settings2",
        "Shapes",
        "Share",
        "Share2",
        "Sheet",
        "Shell",
        "Shield",
        "ShieldAlert",
        "ShieldBan",
        "ShieldCheck",
        "ShieldEllipsis",
        "ShieldHalf",
        "ShieldMinus",
        "ShieldOff",
        "ShieldPlus",
        "ShieldQuestionMark",
        "ShieldUser",
        "ShieldX",
        "Ship",
        "ShipWheel",
        "Shirt",
        "ShoppingBag",
        "ShoppingBasket",
        "ShoppingCart",
        "Shovel",
        "ShowerHead",
        "Shredder",
        "Shrimp",
        "Shrink",
        "Shrub",
        "Shuffle",
        "Sigma",
        "Signal",
        "SignalHigh",
        "SignalLow",
        "SignalMedium",
        "SignalZero",
        "Signature",
        "Signpost",
        "SignpostBig",
        "Siren",
        "SkipBack",
        "SkipForward",
        "Skull",
        "Slack",
        "Slash",
        "Slice",
        "SlidersHorizontal",
        "SlidersVertical",
        "Smartphone",
        "SmartphoneCharging",
        "SmartphoneNfc",
        "Smile",
        "SmilePlus",
        "Snail",
        "Snowflake",
        "SoapDispenserDroplet",
        "Sofa",
        "SolarPanel",
        "Soup",
        "Space",
        "Spade",
        "Sparkle",
        "Sparkles",
        "Speaker",
        "Speech",
        "SpellCheck",
        "SpellCheck2",
        "Spline",
        "SplinePointer",
        "Split",
        "Spool",
        "Spotlight",
        "SprayCan",
        "Sprout",
        "Square",
        "SquareActivity",
        "SquareArrowDown",
        "SquareArrowDownLeft",
        "SquareArrowDownRight",
        "SquareArrowLeft",
        "SquareArrowOutDownLeft",
        "SquareArrowOutDownRight",
        "SquareArrowOutUpLeft",
        "SquareArrowOutUpRight",
        "SquareArrowRight",
        "SquareArrowUp",
        "SquareArrowUpLeft",
        "SquareArrowUpRight",
        "SquareAsterisk",
        "SquareBottomDashedScissors",
        "SquareChartGantt",
        "SquareCheck",
        "SquareCheckBig",
        "SquareChevronDown",
        "SquareChevronLeft",
        "SquareChevronRight",
        "SquareChevronUp",
        "SquareCode",
        "SquareDashed",
        "SquareDashedBottom",
        "SquareDashedBottomCode",
        "SquareDashedKanban",
        "SquareDashedMousePointer",
        "SquareDashedTopSolid",
        "SquareDivide",
        "SquareDot",
        "SquareEqual",
        "SquareFunction",
        "SquareKanban",
        "SquareLibrary",
        "SquareM",
        "SquareMenu",
        "SquareMinus",
        "SquareMousePointer",
        "SquareParking",
        "SquareParkingOff",
        "SquarePause",
        "SquarePen",
        "SquarePercent",
        "SquarePi",
        "SquarePilcrow",
        "SquarePlay",
        "SquarePlus",
        "SquarePower",
        "SquareRadical",
        "SquareRoundCorner",
        "SquareScissors",
        "SquaresExclude",
        "SquareSigma",
        "SquaresIntersect",
        "SquareSlash",
        "SquareSplitHorizontal",
        "SquareSplitVertical",
        "SquareSquare",
        "SquaresSubtract",
        "SquareStack",
        "SquareStar",
        "SquareStop",
        "SquaresUnite",
        "SquareTerminal",
        "SquareUser",
        "SquareUserRound",
        "SquareX",
        "Squircle",
        "SquircleDashed",
        "Squirrel",
        "Stamp",
        "Star",
        "StarHalf",
        "StarOff",
        "StepBack",
        "StepForward",
        "Stethoscope",
        "Sticker",
        "StickyNote",
        "Stone",
        "Store",
        "StretchHorizontal",
        "StretchVertical",
        "Strikethrough",
        "Subscript",
        "Sun",
        "SunDim",
        "SunMedium",
        "SunMoon",
        "Sunrise",
        "Sunset",
        "SunSnow",
        "Superscript",
        "SwatchBook",
        "SwissFranc",
        "SwitchCamera",
        "Sword",
        "Swords",
        "Syringe",
        "Table",
        "Table2",
        "TableCellsMerge",
        "TableCellsSplit",
        "TableColumnsSplit",
        "TableOfContents",
        "TableProperties",
        "TableRowsSplit",
        "Tablet",
        "Tablets",
        "TabletSmartphone",
        "Tag",
        "Tags",
        "Tally1",
        "Tally2",
        "Tally3",
        "Tally4",
        "Tally5",
        "Tangent",
        "Target",
        "Telescope",
        "Tent",
        "TentTree",
        "Terminal",
        "TestTube",
        "TestTubeDiagonal",
        "TestTubes",
        "TextAlignCenter",
        "TextAlignEnd",
        "TextAlignJustify",
        "TextAlignStart",
        "TextCursor",
        "TextCursorInput",
        "TextInitial",
        "TextQuote",
        "TextSearch",
        "TextSelect",
        "TextWrap",
        "Theater",
        "Thermometer",
        "ThermometerSnowflake",
        "ThermometerSun",
        "ThumbsDown",
        "ThumbsUp",
        "Ticket",
        "TicketCheck",
        "TicketMinus",
        "TicketPercent",
        "TicketPlus",
        "Tickets",
        "TicketSlash",
        "TicketsPlane",
        "TicketX",
        "Timer",
        "TimerOff",
        "TimerReset",
        "ToggleLeft",
        "ToggleRight",
        "Toilet",
        "Toolbox",
        "ToolCase",
        "Tornado",
        "Torus",
        "Touchpad",
        "TouchpadOff",
        "TowerControl",
        "ToyBrick",
        "Tractor",
        "TrafficCone",
        "TrainFront",
        "TrainFrontTunnel",
        "TrainTrack",
        "TramFront",
        "Transgender",
        "Trash",
        "Trash2",
        "TreeDeciduous",
        "TreePalm",
        "TreePine",
        "Trees",
        "Trello",
        "TrendingDown",
        "TrendingUp",
        "TrendingUpDown",
        "Triangle",
        "TriangleAlert",
        "TriangleDashed",
        "TriangleRight",
        "Trophy",
        "Truck",
        "TruckElectric",
        "TurkishLira",
        "Turntable",
        "Turtle",
        "Tv",
        "TvMinimal",
        "TvMinimalPlay",
        "Twitch",
        "Twitter",
        "Type",
        "TypeOutline",
        "Umbrella",
        "UmbrellaOff",
        "Underline",
        "Undo",
        "Undo2",
        "UndoDot",
        "UnfoldHorizontal",
        "UnfoldVertical",
        "Ungroup",
        "University",
        "Unlink",
        "Unlink2",
        "Unplug",
        "Upload",
        "Usb",
        "User",
        "UserCheck",
        "UserCog",
        "UserLock",
        "UserMinus",
        "UserPen",
        "UserPlus",
        "UserRound",
        "UserRoundCheck",
        "UserRoundCog",
        "UserRoundMinus",
        "UserRoundPen",
        "UserRoundPlus",
        "UserRoundSearch",
        "UserRoundX",
        "Users",
        "UserSearch",
        "UsersRound",
        "UserStar",
        "UserX",
        "Utensils",
        "UtensilsCrossed",
        "UtilityPole",
        "Van",
        "Variable",
        "Vault",
        "VectorSquare",
        "Vegan",
        "VenetianMask",
        "Venus",
        "VenusAndMars",
        "Vibrate",
        "VibrateOff",
        "Video",
        "VideoOff",
        "Videotape",
        "View",
        "Voicemail",
        "Volleyball",
        "Volume",
        "Volume1",
        "Volume2",
        "VolumeOff",
        "VolumeX",
        "Vote",
        "Wallet",
        "WalletCards",
        "WalletMinimal",
        "Wallpaper",
        "Wand",
        "WandSparkles",
        "Warehouse",
        "WashingMachine",
        "Watch",
        "Waves",
        "WavesArrowDown",
        "WavesArrowUp",
        "WavesLadder",
        "Waypoints",
        "Webcam",
        "Webhook",
        "WebhookOff",
        "Weight",
        "WeightTilde",
        "Wheat",
        "WheatOff",
        "WholeWord",
        "Wifi",
        "WifiCog",
        "WifiHigh",
        "WifiLow",
        "WifiOff",
        "WifiPen",
        "WifiSync",
        "WifiZero",
        "Wind",
        "WindArrowDown",
        "Wine",
        "WineOff",
        "Workflow",
        "Worm",
        "Wrench",
        "X",
        "Youtube",
        "Zap",
        "ZapOff",
        "ZoomIn",
        "ZoomOut"
      ]
    },
    "public.enum_doc_versions_status": {
      "name": "enum_doc_versions_status",
      "schema": "public",
      "values": [
        "draft",
        "published"
      ]
    },
    "public.enum_doc_pages_status": {
      "name": "enum_doc_pages_status",
      "schema": "public",
      "values": [
        "draft",
        "published"
      ]
    }
  },
  "schemas": {},
  "sequences": {},
  "roles": {},
  "policies": {},
  "views": {},
  "_meta": {
    "schemas": {},
    "tables": {},
    "columns": {}
  },
  "id": "499446a1-19f3-4afa-a8dc-2af990b62aea",
  "prevId": "00000000-0000-0000-0000-000000000000"
}